epyk_jqueryui/UI.py
epyk_jqueryui/__init__.py
epyk_jqueryui/_version.py
epyk_jqueryui/css/JqStyleWidget.py
epyk_jqueryui/css/__init__.py
epyk_jqueryui/html/HtmlJqUIWidgets.py
epyk_jqueryui/html/__init__.py
epyk_jqueryui/js/JsJqWidgets.py
epyk_jqueryui/js/__init__.py
epyk_jqueryui/options/OptJqWiidgets.py
epyk_jqueryui/options/__init__.py
epyk_jqueryui-0.0.1.dist-info/LICENSE
epyk_jqueryui-0.0.1.dist-info/METADATA
epyk_jqueryui-0.0.1.dist-info/WHEEL
epyk_jqueryui-0.0.1.dist-info/top_level.txt
epyk_jqueryui-0.0.1.dist-info/RECORD
