Metadata-Version: 2.1
Name: epyk-jqueryui
Version: 0.0.1
Summary: Jquery UI extensions for Epyk
Home-page: https://github.com/epykure/epyk-jqueryui
Author: epykure
Author-email: smith.pyotr@gmail.com
Project-URL: Documentation, http://www.epyk.io
Project-URL: Library, https://jqueryui.com/
Project-URL: Code, https://github.com/epykure/epyk-jqueryui
Classifier: Programming Language :: Python :: 3
Classifier: License :: OSI Approved :: GNU General Public License (GPL)
Classifier: Operating System :: OS Independent
Requires-Python: >=3.8
License-File: LICENSE
Requires-Dist: epyk
